RTL/mac_unit.v
module mac_unit #(
    parameter DATA_WIDTH = 8,
    parameter ACC_WIDTH  = 32
)(
    input  wire clk,
    input  wire rst,
    input  wire enable,
    input  wire clear,

    input  wire signed [DATA_WIDTH-1:0] a,
    input  wire signed [DATA_WIDTH-1:0] b,

    output reg  signed [ACC_WIDTH-1:0] acc_out
);

    always @(posedge clk) begin
        if (rst) begin
            acc_out <= 0;
        end 
        else if (clear) begin
            acc_out <= 0;
        end 
        else if (enable) begin
            acc_out <= acc_out + (a * b); 
        end
    end

endmodule

TestBenchs/mac_tb.v
`timescale 1ns/1ps

module mac_tb;

    parameter DATA_WIDTH = 8;
    parameter ACC_WIDTH  = 32;

    reg clk;
    reg rst;
    reg enable;
    reg clear;
    reg signed [DATA_WIDTH-1:0] a;
    reg signed [DATA_WIDTH-1:0] b;

    wire signed [ACC_WIDTH-1:0] acc_out;

    mac_unit #(DATA_WIDTH, ACC_WIDTH) uut (
        .clk(clk),
        .rst(rst),
        .enable(enable),
        .clear(clear),
        .a(a),
        .b(b),
        .acc_out(acc_out)
    );

    // Clock generation
    always #5 clk = ~clk;

    // Dump file
    initial begin
        $dumpfile("mac.vcd");
        $dumpvars(0, mac_tb);
    end

    // Task (clock-synchronous)
    task apply_input;
        input signed [7:0] in_a;
        input signed [7:0] in_b;
        begin
            // Step 1: Apply inputs BEFORE clock edge
            @(negedge clk);
            a = in_a;
            b = in_b;
            enable = 1;

            // Step 2: Let MAC execute at next posedge
            @(posedge clk);

            // Step 3: Disable enable BEFORE next posedge
            @(negedge clk);
            enable = 0;
        end
    endtask

    initial begin
        clk = 0;
        rst = 1;
        enable = 0;
        clear = 0;
        a = 0;
        b = 0;

        // Reset
        repeat(2) @(posedge clk);
        rst = 0;

        $display("---- TEST START ----");

        // Test 1
        apply_input(2, 3);
        apply_input(4, 5);
        apply_input(1, 1);

        // Clear
        clear = 1;
        @(posedge clk);
        clear = 0;

        // Test 2 (signed)
        apply_input(-2, 3);
        apply_input(3, -4);

        // Enable OFF
        @(posedge clk);
        enable = 0;
        a = 10;
        b = 10;

        @(posedge clk);

        // Reset again
        rst = 1;
        @(posedge clk);
        rst = 0;

        $display("---- TEST END ----");
        $finish;
    end

    initial begin
        $monitor("Time=%0t | a=%d b=%d | acc_out=%d",
                  $time, a, b, acc_out);
    end

endmodule

Waveform/mac.vcd
$date
	Sun Mar 29 09:30:22 2026
$end
$version
	Icarus Verilog
$end
$timescale
	1ps
$end
$scope module mac_tb $end
$var wire 32 ! acc_out [31:0] $end
$var parameter 32 " ACC_WIDTH $end
$var parameter 32 # DATA_WIDTH $end
$var reg 8 $ a [7:0] $end
$var reg 8 % b [7:0] $end
$var reg 1 & clear $end
$var reg 1 ' clk $end
$var reg 1 ( enable $end
$var reg 1 ) rst $end
$scope module uut $end
$var wire 8 * a [7:0] $end
$var wire 8 + b [7:0] $end
$var wire 1 & clear $end
$var wire 1 ' clk $end
$var wire 1 ( enable $end
$var wire 1 ) rst $end
$var parameter 32 , ACC_WIDTH $end
$var parameter 32 - DATA_WIDTH $end
$var reg 32 . acc_out [31:0] $end
$upscope $end
$scope task apply_input $end
$var reg 8 / in_a [7:0] $end
$var reg 8 0 in_b [7:0] $end
$upscope $end
$upscope $end
$enddefinitions $end
$comment Show the parameter values. $end
$dumpall
b1000 -
b100000 ,
b1000 #
b100000 "
$end
#0
$dumpvars
bx 0
bx /
bx .
b0 +
b0 *
1)
0(
0'
0&
b0 %
b0 $
bx !
$end
#5000
b0 !
b0 .
1'
#10000
0'
#15000
b11 0
b10 /
0)
1'
#20000
1(
b11 %
b11 +
b10 $
b10 *
0'
#25000
b110 !
b110 .
1'
#30000
b101 0
b100 /
0(
0'
#35000
1'
#40000
1(
b101 %
b101 +
b100 $
b100 *
0'
#45000
b11010 !
b11010 .
1'
#50000
b1 0
b1 /
0(
0'
#55000
1'
#60000
1(
b1 %
b1 +
b1 $
b1 *
0'
#65000
b11011 !
b11011 .
1'
#70000
1&
0(
0'
#75000
b11 0
b11111110 /
0&
1'
#80000
1(
b11 %
b11 +
b11111110 $
b11111110 *
0'
#85000
b10101 !
b10101 .
1'
#90000
b11111100 0
b11 /
0(
0'
#95000
1'
#100000
1(
b11111100 %
b11111100 +
b11 $
b11 *
0'
#105000
b1001 !
b1001 .
1'
#110000
0(
0'
#115000
b1010 %
b1010 +
b1010 $
b1010 *
1'
#120000
0'
#125000
1)
1'
#130000
0'
#135000
0)
1'
