RTL/memory.v
module memory #(
    parameter DATA_WIDTH = 8,
    parameter ROWS = 4,
    parameter COLS = 4,
    parameter ADDR_WIDTH = 4   // enough for 16 locations
)(
    input wire clk,
    input wire rst,          
    input wire clear,        

    // Write interface
    input wire write_en,
    input wire [ADDR_WIDTH-1:0] addr,
    input wire signed [DATA_WIDTH-1:0] data_in,

    // Parallel read interface
    input wire read_en,

    output reg signed [DATA_WIDTH-1:0] data_out [0:ROWS-1][0:COLS-1]
);

    // Internal memory
    reg signed [DATA_WIDTH-1:0] mem [0:(ROWS*COLS)-1];

    integer i, j;

    // =========================
    // WRITE + RESET + CLEAR
    // =========================
    always @(posedge clk) begin
        if (rst || clear) begin
            for (i = 0; i < ROWS*COLS; i = i + 1)
                mem[i] <= 0;
        end
        else if (write_en) begin
            mem[addr] <= data_in;
        end
    end

    // =========================
    // READ + RESET + CLEAR
    // =========================
    always @(posedge clk) begin
        if (rst || clear) begin
            for (i = 0; i < ROWS; i = i + 1)
                for (j = 0; j < COLS; j = j + 1)
                    data_out[i][j] <= 0;
        end
        else if (read_en) begin
            for (i = 0; i < ROWS; i = i + 1) begin
                for (j = 0; j < COLS; j = j + 1) begin
                    data_out[i][j] <= mem[i*COLS + j];
                end
            end
        end
    end

    // ==============================
    // DEBUG WIRES OF INTERNAL MEMORY
    // ==============================
    wire signed [DATA_WIDTH-1:0] mem0  = mem[0];
    wire signed [DATA_WIDTH-1:0] mem1  = mem[1];
    wire signed [DATA_WIDTH-1:0] mem2  = mem[2];
    wire signed [DATA_WIDTH-1:0] mem3  = mem[3];
    wire signed [DATA_WIDTH-1:0] mem4  = mem[4];
    wire signed [DATA_WIDTH-1:0] mem5  = mem[5];
    wire signed [DATA_WIDTH-1:0] mem6  = mem[6];
    wire signed [DATA_WIDTH-1:0] mem7  = mem[7];
    wire signed [DATA_WIDTH-1:0] mem8  = mem[8];
    wire signed [DATA_WIDTH-1:0] mem9  = mem[9];
    wire signed [DATA_WIDTH-1:0] mem10 = mem[10];
    wire signed [DATA_WIDTH-1:0] mem11 = mem[11];
    wire signed [DATA_WIDTH-1:0] mem12 = mem[12];
    wire signed [DATA_WIDTH-1:0] mem13 = mem[13];
    wire signed [DATA_WIDTH-1:0] mem14 = mem[14];
    wire signed [DATA_WIDTH-1:0] mem15 = mem[15];

endmodule

TestBenchs/memory_tb.v
`timescale 1ns/1ps

module memory_tb;

    parameter DATA_WIDTH = 8;
    parameter ROWS = 4;
    parameter COLS = 4;
    parameter ADDR_WIDTH = 4;

    reg clk;
    reg rst;          
    reg clear;        
    reg write_en;
    reg read_en;
    reg [ADDR_WIDTH-1:0] addr;
    reg signed [DATA_WIDTH-1:0] data_in;

    // 2D output
    wire signed [DATA_WIDTH-1:0] data_out [0:ROWS-1][0:COLS-1];

    // DUT
    memory #(DATA_WIDTH, ROWS, COLS, ADDR_WIDTH) uut (
        .clk(clk),
        .rst(rst),           
        .clear(clear),        
        .write_en(write_en),
        .read_en(read_en),
        .addr(addr),
        .data_in(data_in),
        .data_out(data_out)
    );

    // Clock
    always #5 clk = ~clk;

    integer i, j;

    // Dump
    initial begin
        $dumpfile("memory.vcd");
        $dumpvars(0, memory_tb);
    end

    // =========================
    // TASK: Write full matrix
    // =========================
    task write_matrix;
        input integer base_val;
        integer k;
        begin
            for (k = 0; k < ROWS*COLS; k = k + 1) begin
                @(negedge clk);
                write_en = 1;
                read_en  = 0;
                addr     = k;
                data_in  = base_val + k;

                @(posedge clk);
            end

            @(negedge clk);
            write_en = 0;
        end
    endtask

    // =========================
    // TASK: Read matrix
    // =========================
    task read_matrix;
        begin
            @(negedge clk);
            read_en = 1;

            @(posedge clk);
            @(posedge clk);   // pipeline settle

            @(negedge clk);
            read_en = 0;
        end
    endtask

    // =========================
    // PRINT MATRIX
    // =========================
    task print_matrix;
        begin
            $display("---- MATRIX OUTPUT ----");
            for (i = 0; i < ROWS; i = i + 1) begin
                for (j = 0; j < COLS; j = j + 1) begin
                    $write("%4d ", data_out[i][j]);
                end
                $write("\n");
            end
        end
    endtask

    // =========================
    // TEST SEQUENCE
    // =========================
    initial begin
        clk = 0;
        rst = 1;          
        clear = 0;
        write_en = 0;
        read_en = 0;
        addr = 0;
        data_in = 0;

        // Apply reset
        repeat(2) @(posedge clk);
        rst = 0;

        $display("==== MEMORY TEST START ====");

        // =========================
        // TEST 0: After reset
        // =========================
        read_matrix;
        print_matrix;   

        // =========================
        // TEST 1: Write 0..15
        // =========================
        write_matrix(0);
        read_matrix;
        print_matrix;

        // =========================
        // TEST 2: Overwrite (10..25)
        // =========================
        write_matrix(10);
        read_matrix;
        print_matrix;

        // =========================
        // TEST 3: Clear memory
        // =========================
        @(negedge clk);
        clear = 1;
        @(posedge clk);
        @(negedge clk);
        clear = 0;

        read_matrix;
        print_matrix;   

        // =========================
        // TEST 4: Signed values
        // =========================
        write_matrix(-8);
        read_matrix;
        print_matrix;

        $display("==== MEMORY TEST END ====");
        $finish;
    end

endmodule

Waveform/memory.vcd
$date
	Thu Apr  2 14:49:26 2026
$end
$version
	Icarus Verilog
$end
$timescale
	1ps
$end
$scope module memory_tb $end
$var parameter 32 ! ADDR_WIDTH $end
$var parameter 32 " COLS $end
$var parameter 32 # DATA_WIDTH $end
$var parameter 32 $ ROWS $end
$var reg 4 % addr [3:0] $end
$var reg 1 & clear $end
$var reg 1 ' clk $end
$var reg 8 ( data_in [7:0] $end
$var reg 1 ) read_en $end
$var reg 1 * rst $end
$var reg 1 + write_en $end
$var integer 32 , i [31:0] $end
$var integer 32 - j [31:0] $end
$scope module uut $end
$var wire 4 . addr [3:0] $end
$var wire 1 & clear $end
$var wire 1 ' clk $end
$var wire 8 / data_in [7:0] $end
$var wire 8 0 mem0 [7:0] $end
$var wire 8 1 mem1 [7:0] $end
$var wire 8 2 mem10 [7:0] $end
$var wire 8 3 mem11 [7:0] $end
$var wire 8 4 mem12 [7:0] $end
$var wire 8 5 mem13 [7:0] $end
$var wire 8 6 mem14 [7:0] $end
$var wire 8 7 mem15 [7:0] $end
$var wire 8 8 mem2 [7:0] $end
$var wire 8 9 mem3 [7:0] $end
$var wire 8 : mem4 [7:0] $end
$var wire 8 ; mem5 [7:0] $end
$var wire 8 < mem6 [7:0] $end
$var wire 8 = mem7 [7:0] $end
$var wire 8 > mem8 [7:0] $end
$var wire 8 ? mem9 [7:0] $end
$var wire 1 ) read_en $end
$var wire 1 * rst $end
$var wire 1 + write_en $end
$var parameter 32 @ ADDR_WIDTH $end
$var parameter 32 A COLS $end
$var parameter 32 B DATA_WIDTH $end
$var parameter 32 C ROWS $end
$var integer 32 D i [31:0] $end
$var integer 32 E j [31:0] $end
$upscope $end
$scope task print_matrix $end
$upscope $end
$scope task read_matrix $end
$upscope $end
$scope task write_matrix $end
$var integer 32 F base_val [31:0] $end
$var integer 32 G k [31:0] $end
$upscope $end
$upscope $end
$enddefinitions $end
$comment Show the parameter values. $end
$dumpall
b100 C
b1000 B
b100 A
b100 @
b100 $
b1000 #
b100 "
b100 !
$end
#0
$dumpvars
bx G
bx F
bx E
bx D
bx ?
bx >
bx =
bx <
bx ;
bx :
bx 9
bx 8
bx 7
bx 6
bx 5
bx 4
bx 3
bx 2
bx 1
bx 0
b0 /
b0 .
bx -
bx ,
0+
1*
0)
b0 (
0'
0&
b0 %
$end
#5000
b0 7
b0 6
b0 5
b0 4
b0 3
b0 2
b0 ?
b0 >
b0 =
b0 <
b0 ;
b0 :
b0 9
b0 8
b0 1
b0 0
b100 E
b10000 D
1'
#10000
0'
#15000
0*
b100 E
b100 D
1'
#20000
1)
0'
#25000
b100 E
b100 D
1'
#30000
0'
#35000
b100 E
b100 D
1'
#40000
b0 G
b0 F
b100 -
b100 ,
0)
0'
#45000
1'
#50000
1+
0'
#55000
b1 G
1'
#60000
b1 (
b1 /
b1 %
b1 .
0'
#65000
b1 1
b10 G
1'
#70000
b10 (
b10 /
b10 %
b10 .
0'
#75000
b10 8
b11 G
1'
#80000
b11 (
b11 /
b11 %
b11 .
0'
#85000
b11 9
b100 G
1'
#90000
b100 (
b100 /
b100 %
b100 .
0'
#95000
b100 :
b101 G
1'
#100000
b101 (
b101 /
b101 %
b101 .
0'
#105000
b101 ;
b110 G
1'
#110000
b110 (
b110 /
b110 %
b110 .
0'
#115000
b110 <
b111 G
1'
#120000
b111 (
b111 /
b111 %
b111 .
0'
#125000
b111 =
b1000 G
1'
#130000
b1000 (
b1000 /
b1000 %
b1000 .
0'
#135000
b1000 >
b1001 G
1'
#140000
b1001 (
b1001 /
b1001 %
b1001 .
0'
#145000
b1001 ?
b1010 G
1'
#150000
b1010 (
b1010 /
b1010 %
b1010 .
0'
#155000
b1010 2
b1011 G
1'
#160000
b1011 (
b1011 /
b1011 %
b1011 .
0'
#165000
b1011 3
b1100 G
1'
#170000
b1100 (
b1100 /
b1100 %
b1100 .
0'
#175000
b1100 4
b1101 G
1'
#180000
b1101 (
b1101 /
b1101 %
b1101 .
0'
#185000
b1101 5
b1110 G
1'
#190000
b1110 (
b1110 /
b1110 %
b1110 .
0'
#195000
b1110 6
b1111 G
1'
#200000
b1111 (
b1111 /
b1111 %
b1111 .
0'
#205000
b1111 7
b10000 G
1'
#210000
0+
0'
#215000
1'
#220000
1)
0'
#225000
b100 E
b100 D
1'
#230000
0'
#235000
b100 E
b100 D
1'
#240000
b0 G
b1010 F
b100 -
b100 ,
0)
0'
#245000
1'
#250000
b1010 (
b1010 /
b0 %
b0 .
1+
0'
#255000
b1010 0
b1 G
1'
#260000
b1011 (
b1011 /
b1 %
b1 .
0'
#265000
b1011 1
b10 G
1'
#270000
b1100 (
b1100 /
b10 %
b10 .
0'
#275000
b1100 8
b11 G
1'
#280000
b1101 (
b1101 /
b11 %
b11 .
0'
#285000
b1101 9
b100 G
1'
#290000
b1110 (
b1110 /
b100 %
b100 .
0'
#295000
b1110 :
b101 G
1'
#300000
b1111 (
b1111 /
b101 %
b101 .
0'
#305000
b1111 ;
b110 G
1'
#310000
b10000 (
b10000 /
b110 %
b110 .
0'
#315000
b10000 <
b111 G
1'
#320000
b10001 (
b10001 /
b111 %
b111 .
0'
#325000
b10001 =
b1000 G
1'
#330000
b10010 (
b10010 /
b1000 %
b1000 .
0'
#335000
b10010 >
b1001 G
1'
#340000
b10011 (
b10011 /
b1001 %
b1001 .
0'
#345000
b10011 ?
b1010 G
1'
#350000
b10100 (
b10100 /
b1010 %
b1010 .
0'
#355000
b10100 2
b1011 G
1'
#360000
b10101 (
b10101 /
b1011 %
b1011 .
0'
#365000
b10101 3
b1100 G
1'
#370000
b10110 (
b10110 /
b1100 %
b1100 .
0'
#375000
b10110 4
b1101 G
1'
#380000
b10111 (
b10111 /
b1101 %
b1101 .
0'
#385000
b10111 5
b1110 G
1'
#390000
b11000 (
b11000 /
b1110 %
b1110 .
0'
#395000
b11000 6
b1111 G
1'
#400000
b11001 (
b11001 /
b1111 %
b1111 .
0'
#405000
b11001 7
b10000 G
1'
#410000
0+
0'
#415000
1'
#420000
1)
0'
#425000
b100 E
b100 D
1'
#430000
0'
#435000
b100 E
b100 D
1'
#440000
b100 -
b100 ,
0)
0'
#445000
1'
#450000
1&
0'
#455000
b0 7
b0 6
b0 5
b0 4
b0 3
b0 2
b0 ?
b0 >
b0 =
b0 <
b0 ;
b0 :
b0 9
b0 8
b0 1
b0 0
b100 E
b100 D
1'
#460000
0&
0'
#465000
1'
#470000
1)
0'
#475000
b100 E
b100 D
1'
#480000
0'
#485000
b100 E
b100 D
1'
#490000
b0 G
b11111111111111111111111111111000 F
b100 -
b100 ,
0)
0'
#495000
1'
#500000
b11111000 (
b11111000 /
b0 %
b0 .
1+
0'
#505000
b11111000 0
b1 G
1'
#510000
b11111001 (
b11111001 /
b1 %
b1 .
0'
#515000
b11111001 1
b10 G
1'
#520000
b11111010 (
b11111010 /
b10 %
b10 .
0'
#525000
b11111010 8
b11 G
1'
#530000
b11111011 (
b11111011 /
b11 %
b11 .
0'
#535000
b11111011 9
b100 G
1'
#540000
b11111100 (
b11111100 /
b100 %
b100 .
0'
#545000
b11111100 :
b101 G
1'
#550000
b11111101 (
b11111101 /
b101 %
b101 .
0'
#555000
b11111101 ;
b110 G
1'
#560000
b11111110 (
b11111110 /
b110 %
b110 .
0'
#565000
b11111110 <
b111 G
1'
#570000
b11111111 (
b11111111 /
b111 %
b111 .
0'
#575000
b11111111 =
b1000 G
1'
#580000
b0 (
b0 /
b1000 %
b1000 .
0'
#585000
b1001 G
1'
#590000
b1 (
b1 /
b1001 %
b1001 .
0'
#595000
b1 ?
b1010 G
1'
#600000
b10 (
b10 /
b1010 %
b1010 .
0'
#605000
b10 2
b1011 G
1'
#610000
b11 (
b11 /
b1011 %
b1011 .
0'
#615000
b11 3
b1100 G
1'
#620000
b100 (
b100 /
b1100 %
b1100 .
0'
#625000
b100 4
b1101 G
1'
#630000
b101 (
b101 /
b1101 %
b1101 .
0'
#635000
b101 5
b1110 G
1'
#640000
b110 (
b110 /
b1110 %
b1110 .
0'
#645000
b110 6
b1111 G
1'
#650000
b111 (
b111 /
b1111 %
b1111 .
0'
#655000
b111 7
b10000 G
1'
#660000
0+
0'
#665000
1'
#670000
1)
0'
#675000
b100 E
b100 D
1'
#680000
0'
#685000
b100 E
b100 D
1'
#690000
b100 -
b100 ,
0)
0'
