RTL/mac_unit.v
module mac_unit #(
    parameter DATA_WIDTH = 8,
    parameter ACC_WIDTH  = 32
)(
    input  wire clk,
    input  wire rst,
    input  wire enable,
    input  wire clear,

    input  wire signed [DATA_WIDTH-1:0] a,
    input  wire signed [DATA_WIDTH-1:0] b,

    output reg  signed [ACC_WIDTH-1:0] acc_out
);

    always @(posedge clk) begin
        if (rst) begin
            acc_out <= 0;
        end 
        else if (clear) begin
            acc_out <= 0;
        end 
        else if (enable) begin
            acc_out <= acc_out + (a * b); 
        end
    end

endmodule

RTL/pe_unit.v
module pe_unit #(
    parameter DATA_WIDTH = 8,
    parameter ACC_WIDTH  = 32
)(
    input wire clk,
    input wire rst,

    // Control signals
    input wire enable,
    input wire clear,
    input wire load_a,
    input wire load_b,

    // Inputs
    input wire signed [DATA_WIDTH-1:0] a_in,
    input wire signed [DATA_WIDTH-1:0] b_in,

    // Output
    output wire signed [ACC_WIDTH-1:0] acc_out
);

    // Internal registers
    reg signed [DATA_WIDTH-1:0] a_reg;
    reg signed [DATA_WIDTH-1:0] b_reg;

    // Load registers
    always @(posedge clk) begin
        if (rst) begin
            a_reg <= 0;
            b_reg <= 0;
        end
        else begin
            if (load_a)
                a_reg <= a_in;

            if (load_b)
                b_reg <= b_in;
        end
    end

    // MAC instance
    mac_unit #(
        .DATA_WIDTH(DATA_WIDTH),
        .ACC_WIDTH(ACC_WIDTH)
    ) mac_inst (
        .clk(clk),
        .rst(rst),
        .enable(enable),
        .clear(clear),
        .a(a_reg),
        .b(b_reg),
        .acc_out(acc_out)
    );

endmodule

TestBenchs/pe_tb.v
`timescale 1ns/1ps

module pe_tb;

    parameter DATA_WIDTH = 8;
    parameter ACC_WIDTH  = 32;

    reg clk;
    reg rst;
    reg enable;
    reg clear;
    reg load_a;
    reg load_b;
    reg signed [DATA_WIDTH-1:0] a_in;
    reg signed [DATA_WIDTH-1:0] b_in;

    wire signed [ACC_WIDTH-1:0] acc_out;

    // Instantiate PE
    pe_unit #(DATA_WIDTH, ACC_WIDTH) uut (
        .clk(clk),
        .rst(rst),
        .enable(enable),
        .clear(clear),
        .load_a(load_a),
        .load_b(load_b),
        .a_in(a_in),
        .b_in(b_in),
        .acc_out(acc_out)
    );

    // Clock
    always #5 clk = ~clk;

    // Dump
    initial begin
        $dumpfile("pe.vcd");
        $dumpvars(0, pe_tb);
    end

    // ==============================
    //  TASK: Load A and B together
    // ==============================
    task load_ab;
        input signed [7:0] val_a;
        input signed [7:0] val_b;
        begin
            @(negedge clk);
            a_in = val_a;
            b_in = val_b;
            load_a = 1;
            load_b = 1;

            @(posedge clk);

            @(negedge clk);
            load_a = 0;
            load_b = 0;
        end
    endtask

    // Task: Compute (1 MAC operation)
    task compute_once;
        begin
            @(negedge clk);
            enable = 1;

            @(posedge clk);

            @(negedge clk);
            enable = 0;
        end
    endtask

    initial begin
        clk = 0;
        rst = 1;
        enable = 0;
        clear = 0;
        load_a = 0;
        load_b = 0;
        a_in = 0;
        b_in = 0;

        // Reset
        repeat(2) @(posedge clk);
        rst = 0;

        $display("---- PE TEST START ----");

        // =========================
        // TEST 1: Load and compute
        // =========================
        load_ab(2, 3);
        compute_once;   // 2*3 = 6

        // =========================
        // TEST 2: Accumulation
        // =========================
        load_ab(4, 3);
        compute_once;   // 6 + (4*3) = 18

        load_ab(1, 3);
        compute_once;   // 18 + (1*3) = 21

        // =========================
        // TEST 3: Clear
        // =========================
        @(negedge clk);
        clear = 1;
        @(posedge clk);
        @(negedge clk);
        clear = 0;

        // =========================
        // TEST 4: Signed numbers
        // =========================
        load_ab(-2, 3);
        compute_once;   // -6

        load_ab(3, -4);
        compute_once;   // -6 + (-12) = -18

        // =========================
        // TEST 5: Enable OFF
        // =========================
        @(negedge clk);
        enable = 0;
        a_in = 10;
        b_in = 10;
        @(posedge clk);

        $display("---- PE TEST END ----");
        $finish;
    end

    initial begin
        $monitor("Time=%0t | a_in=%d b_in=%d | acc_out=%d",
                  $time, a_in, b_in, acc_out);
    end

endmodule

Waveform/pe.vcd
$date
	Tue Mar 31 07:28:12 2026
$end
$version
	Icarus Verilog
$end
$timescale
	1ps
$end
$scope module pe_tb $end
$var wire 32 ! acc_out [31:0] $end
$var parameter 32 " ACC_WIDTH $end
$var parameter 32 # DATA_WIDTH $end
$var reg 8 $ a_in [7:0] $end
$var reg 8 % b_in [7:0] $end
$var reg 1 & clear $end
$var reg 1 ' clk $end
$var reg 1 ( enable $end
$var reg 1 ) load_a $end
$var reg 1 * load_b $end
$var reg 1 + rst $end
$scope module uut $end
$var wire 8 , a_in [7:0] $end
$var wire 8 - b_in [7:0] $end
$var wire 1 & clear $end
$var wire 1 ' clk $end
$var wire 1 ( enable $end
$var wire 1 ) load_a $end
$var wire 1 * load_b $end
$var wire 1 + rst $end
$var wire 32 . acc_out [31:0] $end
$var parameter 32 / ACC_WIDTH $end
$var parameter 32 0 DATA_WIDTH $end
$var reg 8 1 a_reg [7:0] $end
$var reg 8 2 b_reg [7:0] $end
$scope module mac_inst $end
$var wire 8 3 a [7:0] $end
$var wire 8 4 b [7:0] $end
$var wire 1 & clear $end
$var wire 1 ' clk $end
$var wire 1 ( enable $end
$var wire 1 + rst $end
$var parameter 32 5 ACC_WIDTH $end
$var parameter 32 6 DATA_WIDTH $end
$var reg 32 7 acc_out [31:0] $end
$upscope $end
$upscope $end
$scope task compute_once $end
$upscope $end
$scope task load_ab $end
$var reg 8 8 val_a [7:0] $end
$var reg 8 9 val_b [7:0] $end
$upscope $end
$upscope $end
$enddefinitions $end
$comment Show the parameter values. $end
$dumpall
b1000 6
b100000 5
b1000 0
b100000 /
b1000 #
b100000 "
$end
#0
$dumpvars
bx 9
bx 8
bx 7
bx 4
bx 3
bx 2
bx 1
bx .
b0 -
b0 ,
1+
0*
0)
0(
0'
0&
b0 %
b0 $
bx !
$end
#5000
b0 !
b0 .
b0 7
b0 2
b0 4
b0 1
b0 3
1'
#10000
0'
#15000
b11 9
b10 8
0+
1'
#20000
1*
1)
b11 %
b11 -
b10 $
b10 ,
0'
#25000
b11 2
b11 4
b10 1
b10 3
1'
#30000
0*
0)
0'
#35000
1'
#40000
1(
0'
#45000
b110 !
b110 .
b110 7
1'
#50000
b100 8
0(
0'
#55000
1'
#60000
1*
1)
b100 $
b100 ,
0'
#65000
b100 1
b100 3
1'
#70000
0*
0)
0'
#75000
1'
#80000
1(
0'
#85000
b10010 !
b10010 .
b10010 7
1'
#90000
b1 8
0(
0'
#95000
1'
#100000
1*
1)
b1 $
b1 ,
0'
#105000
b1 1
b1 3
1'
#110000
0*
0)
0'
#115000
1'
#120000
1(
0'
#125000
b10101 !
b10101 .
b10101 7
1'
#130000
0(
0'
#135000
1'
#140000
1&
0'
#145000
b0 !
b0 .
b0 7
1'
#150000
b11111110 8
0&
0'
#155000
1'
#160000
1*
1)
b11111110 $
b11111110 ,
0'
#165000
b11111110 1
b11111110 3
1'
#170000
0*
0)
0'
#175000
1'
#180000
1(
0'
#185000
b11111111111111111111111111111010 !
b11111111111111111111111111111010 .
b11111111111111111111111111111010 7
1'
#190000
b11111100 9
b11 8
0(
0'
#195000
1'
#200000
1*
1)
b11111100 %
b11111100 -
b11 $
b11 ,
0'
#205000
b11111100 2
b11111100 4
b11 1
b11 3
1'
#210000
0*
0)
0'
#215000
1'
#220000
1(
0'
#225000
b11111111111111111111111111101110 !
b11111111111111111111111111101110 .
b11111111111111111111111111101110 7
1'
#230000
0(
0'
#235000
1'
#240000
b1010 %
b1010 -
b1010 $
b1010 ,
0'
