RTL/mac_unit.v
module mac_unit #(
    parameter DATA_WIDTH = 8,
    parameter ACC_WIDTH  = 32
)(
    input  wire clk,
    input  wire rst,
    input  wire enable,
    input  wire clear,

    input  wire signed [DATA_WIDTH-1:0] a,
    input  wire signed [DATA_WIDTH-1:0] b,

    output reg  signed [ACC_WIDTH-1:0] acc_out
);

    always @(posedge clk) begin
        if (rst) begin
            acc_out <= 0;
        end 
        else if (clear) begin
            acc_out <= 0;
        end 
        else if (enable) begin
            acc_out <= acc_out + (a * b); 
        end
    end

endmodule

RTL/pe_unit.v
module pe_unit #(
    parameter DATA_WIDTH = 8,
    parameter ACC_WIDTH  = 32
)(
    input wire clk,
    input wire rst,

    // Control signals
    input wire enable,
    input wire clear,
    input wire load_a,
    input wire load_b,

    // Inputs
    input wire signed [DATA_WIDTH-1:0] a_in,
    input wire signed [DATA_WIDTH-1:0] b_in,

    // Output
    output wire signed [ACC_WIDTH-1:0] acc_out
);

    // Internal registers
    reg signed [DATA_WIDTH-1:0] a_reg;
    reg signed [DATA_WIDTH-1:0] b_reg;

    // Load registers
    always @(posedge clk) begin
        if (rst) begin
            a_reg <= 0;
            b_reg <= 0;
        end
        else begin
            if (load_a)
                a_reg <= a_in;

            if (load_b)
                b_reg <= b_in;
        end
    end

    // MAC instance
    mac_unit #(
        .DATA_WIDTH(DATA_WIDTH),
        .ACC_WIDTH(ACC_WIDTH)
    ) mac_inst (
        .clk(clk),
        .rst(rst),
        .enable(enable),
        .clear(clear),
        .a(a_reg),
        .b(b_reg),
        .acc_out(acc_out)
    );

endmodule

RTL/pe_array_2d.v
module pe_array_2d #(
    parameter DATA_WIDTH = 8,
    parameter ACC_WIDTH  = 32,
    parameter ROWS = 4,
    parameter COLS = 4
)(
    input wire clk,
    input wire rst,

    // Global control signals
    input wire enable,
    input wire clear,
    input wire load_a,
    input wire load_b,

    // 2D Inputs
    input wire signed [DATA_WIDTH-1:0] a_in [0:ROWS-1][0:COLS-1],
    input wire signed [DATA_WIDTH-1:0] b_in [0:ROWS-1][0:COLS-1],

    // 2D Outputs
    output wire signed [ACC_WIDTH-1:0] acc_out [0:ROWS-1][0:COLS-1]
);

    // Internal wires
    wire signed [ACC_WIDTH-1:0] pe_out [0:ROWS-1][0:COLS-1];

    // Output registers (pipeline stage)
    reg signed [ACC_WIDTH-1:0] acc_reg [0:ROWS-1][0:COLS-1];

    genvar i, j;
    generate
        for (i = 0; i < ROWS; i = i + 1) begin : ROW_BLOCK
            for (j = 0; j < COLS; j = j + 1) begin : COL_BLOCK

                // Instantiate PE
                pe_unit #(
                    .DATA_WIDTH(DATA_WIDTH),
                    .ACC_WIDTH(ACC_WIDTH)
                ) pe_inst (
                    .clk(clk),
                    .rst(rst),
                    .enable(enable),
                    .clear(clear),
                    .load_a(load_a),
                    .load_b(load_b),
                    .a_in(a_in[i][j]),
                    .b_in(b_in[i][j]),
                    .acc_out(pe_out[i][j])
                );

                // Pipeline register
                always @(posedge clk) begin
                    if (rst)
                        acc_reg[i][j] <= 0;
                    else
                        acc_reg[i][j] <= pe_out[i][j];
                end

                // Final output
                assign acc_out[i][j] = acc_reg[i][j];

            end
        end
    endgenerate

endmodule

TestBenchs/pe_array_2d_tb.v
`timescale 1ns/1ps

module pe_array_2d_tb;

    parameter DATA_WIDTH = 8;
    parameter ACC_WIDTH  = 32;
    parameter ROWS = 4;
    parameter COLS = 4;

    reg clk;
    reg rst;
    reg enable;
    reg clear;
    reg load_a;
    reg load_b;

    reg signed [DATA_WIDTH-1:0] a_in [0:ROWS-1][0:COLS-1];
    reg signed [DATA_WIDTH-1:0] b_in [0:ROWS-1][0:COLS-1];

    wire signed [ACC_WIDTH-1:0] acc_out [0:ROWS-1][0:COLS-1];

    pe_array_2d #(DATA_WIDTH, ACC_WIDTH, ROWS, COLS) uut (
        .clk(clk),
        .rst(rst),
        .enable(enable),
        .clear(clear),
        .load_a(load_a),
        .load_b(load_b),
        .a_in(a_in),
        .b_in(b_in),
        .acc_out(acc_out)
    );

    always #5 clk = ~clk;

    initial begin
        $dumpfile("pe_array.vcd");
        $dumpvars(0, pe_array_2d_tb);
    end

    integer i, j;

    // Monitor
    initial begin
        $monitor("Time=%0t | acc_out[0][0]=%d acc_out[1][1]=%d acc_out[3][3]=%d",
                  $time,
                  acc_out[0][0],
                  acc_out[1][1],
                  acc_out[3][3]);
    end

    task load_matrix;
        begin
            @(negedge clk);
            load_a = 1;
            load_b = 1;

            @(posedge clk);

            @(negedge clk);
            load_a = 0;
            load_b = 0;
        end
    endtask

    task compute_once;
        begin
            @(negedge clk);
            enable = 1;

            @(posedge clk);

            @(negedge clk);
            enable = 0;
        end
    endtask

    initial begin
        clk = 0;
        rst = 1;
        enable = 0;
        clear = 0;
        load_a = 0;
        load_b = 0;

        // Initialize
        for (i = 0; i < ROWS; i = i + 1)
            for (j = 0; j < COLS; j = j + 1) begin
                a_in[i][j] = 0;
                b_in[i][j] = 0;
            end

        // Reset
        repeat(2) @(posedge clk);
        rst = 0;

        $display("---- 2D PE ARRAY TEST START ----");

        // =========================
        // TEST 1
        // =========================
        for (i = 0; i < ROWS; i = i + 1)
            for (j = 0; j < COLS; j = j + 1) begin
                a_in[i][j] = i + j;
                b_in[i][j] = 2;
            end

        load_matrix;
        compute_once;
        repeat(2) @(posedge clk);

        $display("---- OUTPUT MATRIX (TEST 1) ----");
        for (i = 0; i < ROWS; i = i + 1) begin
            for (j = 0; j < COLS; j = j + 1)
                $write("%4d ", acc_out[i][j]);
            $write("\n");
        end

        // =========================
        // TEST 2
        // =========================
        for (i = 0; i < ROWS; i = i + 1)
            for (j = 0; j < COLS; j = j + 1) begin
                a_in[i][j] = 1;
                b_in[i][j] = 3;
            end

        load_matrix;
        compute_once;
        repeat(2) @(posedge clk);

        $display("---- OUTPUT MATRIX (TEST 2) ----");
        for (i = 0; i < ROWS; i = i + 1) begin
            for (j = 0; j < COLS; j = j + 1)
                $write("%4d ", acc_out[i][j]);
            $write("\n");
        end

        // =========================
        // TEST 3 (CLEAR)
        // =========================
        @(negedge clk);
        clear = 1;
        @(posedge clk);
        @(negedge clk);
        clear = 0;

        repeat(2) @(posedge clk);

        $display("---- OUTPUT MATRIX (AFTER CLEAR) ----");
        for (i = 0; i < ROWS; i = i + 1) begin
            for (j = 0; j < COLS; j = j + 1)
                $write("%4d ", acc_out[i][j]);
            $write("\n");
        end

        // =========================
        // TEST 4 (SIGNED)
        // =========================
        for (i = 0; i < ROWS; i = i + 1)
            for (j = 0; j < COLS; j = j + 1) begin
                a_in[i][j] = -i;
                b_in[i][j] = j;
            end

        load_matrix;
        compute_once;
        repeat(2) @(posedge clk);

        $display("---- OUTPUT MATRIX (TEST 4 - SIGNED) ----");
        for (i = 0; i < ROWS; i = i + 1) begin
            for (j = 0; j < COLS; j = j + 1)
                $write("%4d ", acc_out[i][j]);
            $write("\n");
        end

        $display("---- TEST END ----");
        $finish;
    end

endmodule

Waveform/pe_array.vcd
$date
	Tue Mar 31 19:00:03 2026
$end
$version
	Icarus Verilog
$end
$timescale
	1ps
$end
$scope module pe_array_2d_tb $end
$var parameter 32 ! ACC_WIDTH $end
$var parameter 32 " COLS $end
$var parameter 32 # DATA_WIDTH $end
$var parameter 32 $ ROWS $end
$var reg 1 % clear $end
$var reg 1 & clk $end
$var reg 1 ' enable $end
$var reg 1 ( load_a $end
$var reg 1 ) load_b $end
$var reg 1 * rst $end
$var integer 32 + i [31:0] $end
$var integer 32 , j [31:0] $end
$scope module uut $end
$var wire 1 % clear $end
$var wire 1 & clk $end
$var wire 1 ' enable $end
$var wire 1 ( load_a $end
$var wire 1 ) load_b $end
$var wire 1 * rst $end
$var parameter 32 - ACC_WIDTH $end
$var parameter 32 . COLS $end
$var parameter 32 / DATA_WIDTH $end
$var parameter 32 0 ROWS $end
$scope begin ROW_BLOCK[0] $end
$var parameter 2 1 i $end
$scope begin COL_BLOCK[0] $end
$var parameter 2 2 j $end
$scope module pe_inst $end
$var wire 8 3 a_in [7:0] $end
$var wire 8 4 b_in [7:0] $end
$var wire 1 % clear $end
$var wire 1 & clk $end
$var wire 1 ' enable $end
$var wire 1 ( load_a $end
$var wire 1 ) load_b $end
$var wire 1 * rst $end
$var wire 32 5 acc_out [31:0] $end
$var parameter 32 6 ACC_WIDTH $end
$var parameter 32 7 DATA_WIDTH $end
$var reg 8 8 a_reg [7:0] $end
$var reg 8 9 b_reg [7:0] $end
$scope module mac_inst $end
$var wire 8 : a [7:0] $end
$var wire 8 ; b [7:0] $end
$var wire 1 % clear $end
$var wire 1 & clk $end
$var wire 1 ' enable $end
$var wire 1 * rst $end
$var parameter 32 < ACC_WIDTH $end
$var parameter 32 = DATA_WIDTH $end
$var reg 32 > acc_out [31:0] $end
$upscope $end
$upscope $end
$upscope $end
$scope begin COL_BLOCK[1] $end
$var parameter 2 ? j $end
$scope module pe_inst $end
$var wire 8 @ a_in [7:0] $end
$var wire 8 A b_in [7:0] $end
$var wire 1 % clear $end
$var wire 1 & clk $end
$var wire 1 ' enable $end
$var wire 1 ( load_a $end
$var wire 1 ) load_b $end
$var wire 1 * rst $end
$var wire 32 B acc_out [31:0] $end
$var parameter 32 C ACC_WIDTH $end
$var parameter 32 D DATA_WIDTH $end
$var reg 8 E a_reg [7:0] $end
$var reg 8 F b_reg [7:0] $end
$scope module mac_inst $end
$var wire 8 G a [7:0] $end
$var wire 8 H b [7:0] $end
$var wire 1 % clear $end
$var wire 1 & clk $end
$var wire 1 ' enable $end
$var wire 1 * rst $end
$var parameter 32 I ACC_WIDTH $end
$var parameter 32 J DATA_WIDTH $end
$var reg 32 K acc_out [31:0] $end
$upscope $end
$upscope $end
$upscope $end
$scope begin COL_BLOCK[2] $end
$var parameter 3 L j $end
$scope module pe_inst $end
$var wire 8 M a_in [7:0] $end
$var wire 8 N b_in [7:0] $end
$var wire 1 % clear $end
$var wire 1 & clk $end
$var wire 1 ' enable $end
$var wire 1 ( load_a $end
$var wire 1 ) load_b $end
$var wire 1 * rst $end
$var wire 32 O acc_out [31:0] $end
$var parameter 32 P ACC_WIDTH $end
$var parameter 32 Q DATA_WIDTH $end
$var reg 8 R a_reg [7:0] $end
$var reg 8 S b_reg [7:0] $end
$scope module mac_inst $end
$var wire 8 T a [7:0] $end
$var wire 8 U b [7:0] $end
$var wire 1 % clear $end
$var wire 1 & clk $end
$var wire 1 ' enable $end
$var wire 1 * rst $end
$var parameter 32 V ACC_WIDTH $end
$var parameter 32 W DATA_WIDTH $end
$var reg 32 X acc_out [31:0] $end
$upscope $end
$upscope $end
$upscope $end
$scope begin COL_BLOCK[3] $end
$var parameter 3 Y j $end
$scope module pe_inst $end
$var wire 8 Z a_in [7:0] $end
$var wire 8 [ b_in [7:0] $end
$var wire 1 % clear $end
$var wire 1 & clk $end
$var wire 1 ' enable $end
$var wire 1 ( load_a $end
$var wire 1 ) load_b $end
$var wire 1 * rst $end
$var wire 32 \ acc_out [31:0] $end
$var parameter 32 ] ACC_WIDTH $end
$var parameter 32 ^ DATA_WIDTH $end
$var reg 8 _ a_reg [7:0] $end
$var reg 8 ` b_reg [7:0] $end
$scope module mac_inst $end
$var wire 8 a a [7:0] $end
$var wire 8 b b [7:0] $end
$var wire 1 % clear $end
$var wire 1 & clk $end
$var wire 1 ' enable $end
$var wire 1 * rst $end
$var parameter 32 c ACC_WIDTH $end
$var parameter 32 d DATA_WIDTH $end
$var reg 32 e acc_out [31:0] $end
$upscope $end
$upscope $end
$upscope $end
$upscope $end
$scope begin ROW_BLOCK[1] $end
$var parameter 2 f i $end
$scope begin COL_BLOCK[0] $end
$var parameter 2 g j $end
$scope module pe_inst $end
$var wire 8 h a_in [7:0] $end
$var wire 8 i b_in [7:0] $end
$var wire 1 % clear $end
$var wire 1 & clk $end
$var wire 1 ' enable $end
$var wire 1 ( load_a $end
$var wire 1 ) load_b $end
$var wire 1 * rst $end
$var wire 32 j acc_out [31:0] $end
$var parameter 32 k ACC_WIDTH $end
$var parameter 32 l DATA_WIDTH $end
$var reg 8 m a_reg [7:0] $end
$var reg 8 n b_reg [7:0] $end
$scope module mac_inst $end
$var wire 8 o a [7:0] $end
$var wire 8 p b [7:0] $end
$var wire 1 % clear $end
$var wire 1 & clk $end
$var wire 1 ' enable $end
$var wire 1 * rst $end
$var parameter 32 q ACC_WIDTH $end
$var parameter 32 r DATA_WIDTH $end
$var reg 32 s acc_out [31:0] $end
$upscope $end
$upscope $end
$upscope $end
$scope begin COL_BLOCK[1] $end
$var parameter 2 t j $end
$scope module pe_inst $end
$var wire 8 u a_in [7:0] $end
$var wire 8 v b_in [7:0] $end
$var wire 1 % clear $end
$var wire 1 & clk $end
$var wire 1 ' enable $end
$var wire 1 ( load_a $end
$var wire 1 ) load_b $end
$var wire 1 * rst $end
$var wire 32 w acc_out [31:0] $end
$var parameter 32 x ACC_WIDTH $end
$var parameter 32 y DATA_WIDTH $end
$var reg 8 z a_reg [7:0] $end
$var reg 8 { b_reg [7:0] $end
$scope module mac_inst $end
$var wire 8 | a [7:0] $end
$var wire 8 } b [7:0] $end
$var wire 1 % clear $end
$var wire 1 & clk $end
$var wire 1 ' enable $end
$var wire 1 * rst $end
$var parameter 32 ~ ACC_WIDTH $end
$var parameter 32 !" DATA_WIDTH $end
$var reg 32 "" acc_out [31:0] $end
$upscope $end
$upscope $end
$upscope $end
$scope begin COL_BLOCK[2] $end
$var parameter 3 #" j $end
$scope module pe_inst $end
$var wire 8 $" a_in [7:0] $end
$var wire 8 %" b_in [7:0] $end
$var wire 1 % clear $end
$var wire 1 & clk $end
$var wire 1 ' enable $end
$var wire 1 ( load_a $end
$var wire 1 ) load_b $end
$var wire 1 * rst $end
$var wire 32 &" acc_out [31:0] $end
$var parameter 32 '" ACC_WIDTH $end
$var parameter 32 (" DATA_WIDTH $end
$var reg 8 )" a_reg [7:0] $end
$var reg 8 *" b_reg [7:0] $end
$scope module mac_inst $end
$var wire 8 +" a [7:0] $end
$var wire 8 ," b [7:0] $end
$var wire 1 % clear $end
$var wire 1 & clk $end
$var wire 1 ' enable $end
$var wire 1 * rst $end
$var parameter 32 -" ACC_WIDTH $end
$var parameter 32 ." DATA_WIDTH $end
$var reg 32 /" acc_out [31:0] $end
$upscope $end
$upscope $end
$upscope $end
$scope begin COL_BLOCK[3] $end
$var parameter 3 0" j $end
$scope module pe_inst $end
$var wire 8 1" a_in [7:0] $end
$var wire 8 2" b_in [7:0] $end
$var wire 1 % clear $end
$var wire 1 & clk $end
$var wire 1 ' enable $end
$var wire 1 ( load_a $end
$var wire 1 ) load_b $end
$var wire 1 * rst $end
$var wire 32 3" acc_out [31:0] $end
$var parameter 32 4" ACC_WIDTH $end
$var parameter 32 5" DATA_WIDTH $end
$var reg 8 6" a_reg [7:0] $end
$var reg 8 7" b_reg [7:0] $end
$scope module mac_inst $end
$var wire 8 8" a [7:0] $end
$var wire 8 9" b [7:0] $end
$var wire 1 % clear $end
$var wire 1 & clk $end
$var wire 1 ' enable $end
$var wire 1 * rst $end
$var parameter 32 :" ACC_WIDTH $end
$var parameter 32 ;" DATA_WIDTH $end
$var reg 32 <" acc_out [31:0] $end
$upscope $end
$upscope $end
$upscope $end
$upscope $end
$scope begin ROW_BLOCK[2] $end
$var parameter 3 =" i $end
$scope begin COL_BLOCK[0] $end
$var parameter 2 >" j $end
$scope module pe_inst $end
$var wire 8 ?" a_in [7:0] $end
$var wire 8 @" b_in [7:0] $end
$var wire 1 % clear $end
$var wire 1 & clk $end
$var wire 1 ' enable $end
$var wire 1 ( load_a $end
$var wire 1 ) load_b $end
$var wire 1 * rst $end
$var wire 32 A" acc_out [31:0] $end
$var parameter 32 B" ACC_WIDTH $end
$var parameter 32 C" DATA_WIDTH $end
$var reg 8 D" a_reg [7:0] $end
$var reg 8 E" b_reg [7:0] $end
$scope module mac_inst $end
$var wire 8 F" a [7:0] $end
$var wire 8 G" b [7:0] $end
$var wire 1 % clear $end
$var wire 1 & clk $end
$var wire 1 ' enable $end
$var wire 1 * rst $end
$var parameter 32 H" ACC_WIDTH $end
$var parameter 32 I" DATA_WIDTH $end
$var reg 32 J" acc_out [31:0] $end
$upscope $end
$upscope $end
$upscope $end
$scope begin COL_BLOCK[1] $end
$var parameter 2 K" j $end
$scope module pe_inst $end
$var wire 8 L" a_in [7:0] $end
$var wire 8 M" b_in [7:0] $end
$var wire 1 % clear $end
$var wire 1 & clk $end
$var wire 1 ' enable $end
$var wire 1 ( load_a $end
$var wire 1 ) load_b $end
$var wire 1 * rst $end
$var wire 32 N" acc_out [31:0] $end
$var parameter 32 O" ACC_WIDTH $end
$var parameter 32 P" DATA_WIDTH $end
$var reg 8 Q" a_reg [7:0] $end
$var reg 8 R" b_reg [7:0] $end
$scope module mac_inst $end
$var wire 8 S" a [7:0] $end
$var wire 8 T" b [7:0] $end
$var wire 1 % clear $end
$var wire 1 & clk $end
$var wire 1 ' enable $end
$var wire 1 * rst $end
$var parameter 32 U" ACC_WIDTH $end
$var parameter 32 V" DATA_WIDTH $end
$var reg 32 W" acc_out [31:0] $end
$upscope $end
$upscope $end
$upscope $end
$scope begin COL_BLOCK[2] $end
$var parameter 3 X" j $end
$scope module pe_inst $end
$var wire 8 Y" a_in [7:0] $end
$var wire 8 Z" b_in [7:0] $end
$var wire 1 % clear $end
$var wire 1 & clk $end
$var wire 1 ' enable $end
$var wire 1 ( load_a $end
$var wire 1 ) load_b $end
$var wire 1 * rst $end
$var wire 32 [" acc_out [31:0] $end
$var parameter 32 \" ACC_WIDTH $end
$var parameter 32 ]" DATA_WIDTH $end
$var reg 8 ^" a_reg [7:0] $end
$var reg 8 _" b_reg [7:0] $end
$scope module mac_inst $end
$var wire 8 `" a [7:0] $end
$var wire 8 a" b [7:0] $end
$var wire 1 % clear $end
$var wire 1 & clk $end
$var wire 1 ' enable $end
$var wire 1 * rst $end
$var parameter 32 b" ACC_WIDTH $end
$var parameter 32 c" DATA_WIDTH $end
$var reg 32 d" acc_out [31:0] $end
$upscope $end
$upscope $end
$upscope $end
$scope begin COL_BLOCK[3] $end
$var parameter 3 e" j $end
$scope module pe_inst $end
$var wire 8 f" a_in [7:0] $end
$var wire 8 g" b_in [7:0] $end
$var wire 1 % clear $end
$var wire 1 & clk $end
$var wire 1 ' enable $end
$var wire 1 ( load_a $end
$var wire 1 ) load_b $end
$var wire 1 * rst $end
$var wire 32 h" acc_out [31:0] $end
$var parameter 32 i" ACC_WIDTH $end
$var parameter 32 j" DATA_WIDTH $end
$var reg 8 k" a_reg [7:0] $end
$var reg 8 l" b_reg [7:0] $end
$scope module mac_inst $end
$var wire 8 m" a [7:0] $end
$var wire 8 n" b [7:0] $end
$var wire 1 % clear $end
$var wire 1 & clk $end
$var wire 1 ' enable $end
$var wire 1 * rst $end
$var parameter 32 o" ACC_WIDTH $end
$var parameter 32 p" DATA_WIDTH $end
$var reg 32 q" acc_out [31:0] $end
$upscope $end
$upscope $end
$upscope $end
$upscope $end
$scope begin ROW_BLOCK[3] $end
$var parameter 3 r" i $end
$scope begin COL_BLOCK[0] $end
$var parameter 2 s" j $end
$scope module pe_inst $end
$var wire 8 t" a_in [7:0] $end
$var wire 8 u" b_in [7:0] $end
$var wire 1 % clear $end
$var wire 1 & clk $end
$var wire 1 ' enable $end
$var wire 1 ( load_a $end
$var wire 1 ) load_b $end
$var wire 1 * rst $end
$var wire 32 v" acc_out [31:0] $end
$var parameter 32 w" ACC_WIDTH $end
$var parameter 32 x" DATA_WIDTH $end
$var reg 8 y" a_reg [7:0] $end
$var reg 8 z" b_reg [7:0] $end
$scope module mac_inst $end
$var wire 8 {" a [7:0] $end
$var wire 8 |" b [7:0] $end
$var wire 1 % clear $end
$var wire 1 & clk $end
$var wire 1 ' enable $end
$var wire 1 * rst $end
$var parameter 32 }" ACC_WIDTH $end
$var parameter 32 ~" DATA_WIDTH $end
$var reg 32 !# acc_out [31:0] $end
$upscope $end
$upscope $end
$upscope $end
$scope begin COL_BLOCK[1] $end
$var parameter 2 "# j $end
$scope module pe_inst $end
$var wire 8 ## a_in [7:0] $end
$var wire 8 $# b_in [7:0] $end
$var wire 1 % clear $end
$var wire 1 & clk $end
$var wire 1 ' enable $end
$var wire 1 ( load_a $end
$var wire 1 ) load_b $end
$var wire 1 * rst $end
$var wire 32 %# acc_out [31:0] $end
$var parameter 32 &# ACC_WIDTH $end
$var parameter 32 '# DATA_WIDTH $end
$var reg 8 (# a_reg [7:0] $end
$var reg 8 )# b_reg [7:0] $end
$scope module mac_inst $end
$var wire 8 *# a [7:0] $end
$var wire 8 +# b [7:0] $end
$var wire 1 % clear $end
$var wire 1 & clk $end
$var wire 1 ' enable $end
$var wire 1 * rst $end
$var parameter 32 ,# ACC_WIDTH $end
$var parameter 32 -# DATA_WIDTH $end
$var reg 32 .# acc_out [31:0] $end
$upscope $end
$upscope $end
$upscope $end
$scope begin COL_BLOCK[2] $end
$var parameter 3 /# j $end
$scope module pe_inst $end
$var wire 8 0# a_in [7:0] $end
$var wire 8 1# b_in [7:0] $end
$var wire 1 % clear $end
$var wire 1 & clk $end
$var wire 1 ' enable $end
$var wire 1 ( load_a $end
$var wire 1 ) load_b $end
$var wire 1 * rst $end
$var wire 32 2# acc_out [31:0] $end
$var parameter 32 3# ACC_WIDTH $end
$var parameter 32 4# DATA_WIDTH $end
$var reg 8 5# a_reg [7:0] $end
$var reg 8 6# b_reg [7:0] $end
$scope module mac_inst $end
$var wire 8 7# a [7:0] $end
$var wire 8 8# b [7:0] $end
$var wire 1 % clear $end
$var wire 1 & clk $end
$var wire 1 ' enable $end
$var wire 1 * rst $end
$var parameter 32 9# ACC_WIDTH $end
$var parameter 32 :# DATA_WIDTH $end
$var reg 32 ;# acc_out [31:0] $end
$upscope $end
$upscope $end
$upscope $end
$scope begin COL_BLOCK[3] $end
$var parameter 3 <# j $end
$scope module pe_inst $end
$var wire 8 =# a_in [7:0] $end
$var wire 8 ># b_in [7:0] $end
$var wire 1 % clear $end
$var wire 1 & clk $end
$var wire 1 ' enable $end
$var wire 1 ( load_a $end
$var wire 1 ) load_b $end
$var wire 1 * rst $end
$var wire 32 ?# acc_out [31:0] $end
$var parameter 32 @# ACC_WIDTH $end
$var parameter 32 A# DATA_WIDTH $end
$var reg 8 B# a_reg [7:0] $end
$var reg 8 C# b_reg [7:0] $end
$scope module mac_inst $end
$var wire 8 D# a [7:0] $end
$var wire 8 E# b [7:0] $end
$var wire 1 % clear $end
$var wire 1 & clk $end
$var wire 1 ' enable $end
$var wire 1 * rst $end
$var parameter 32 F# ACC_WIDTH $end
$var parameter 32 G# DATA_WIDTH $end
$var reg 32 H# acc_out [31:0] $end
$upscope $end
$upscope $end
$upscope $end
$upscope $end
$upscope $end
$scope task compute_once $end
$upscope $end
$scope task load_matrix $end
$upscope $end
$upscope $end
$enddefinitions $end
$comment Show the parameter values. $end
$dumpall
b1000 G#
b100000 F#
b1000 A#
b100000 @#
b11 <#
b1000 :#
b100000 9#
b1000 4#
b100000 3#
b10 /#
b1000 -#
b100000 ,#
b1000 '#
b100000 &#
b1 "#
b1000 ~"
b100000 }"
b1000 x"
b100000 w"
b0 s"
b11 r"
b1000 p"
b100000 o"
b1000 j"
b100000 i"
b11 e"
b1000 c"
b100000 b"
b1000 ]"
b100000 \"
b10 X"
b1000 V"
b100000 U"
b1000 P"
b100000 O"
b1 K"
b1000 I"
b100000 H"
b1000 C"
b100000 B"
b0 >"
b10 ="
b1000 ;"
b100000 :"
b1000 5"
b100000 4"
b11 0"
b1000 ."
b100000 -"
b1000 ("
b100000 '"
b10 #"
b1000 !"
b100000 ~
b1000 y
b100000 x
b1 t
b1000 r
b100000 q
b1000 l
b100000 k
b0 g
b1 f
b1000 d
b100000 c
b1000 ^
b100000 ]
b11 Y
b1000 W
b100000 V
b1000 Q
b100000 P
b10 L
b1000 J
b100000 I
b1000 D
b100000 C
b1 ?
b1000 =
b100000 <
b1000 7
b100000 6
b0 2
b0 1
b100 0
b1000 /
b100 .
b100000 -
b100 $
b1000 #
b100 "
b100000 !
$end
#0
$dumpvars
bx H#
bx E#
bx D#
bx C#
bx B#
bx ?#
b0 >#
b0 =#
bx ;#
bx 8#
bx 7#
bx 6#
bx 5#
bx 2#
b0 1#
b0 0#
bx .#
bx +#
bx *#
bx )#
bx (#
bx %#
b0 $#
b0 ##
bx !#
bx |"
bx {"
bx z"
bx y"
bx v"
b0 u"
b0 t"
bx q"
bx n"
bx m"
bx l"
bx k"
bx h"
b0 g"
b0 f"
bx d"
bx a"
bx `"
bx _"
bx ^"
bx ["
b0 Z"
b0 Y"
bx W"
bx T"
bx S"
bx R"
bx Q"
bx N"
b0 M"
b0 L"
bx J"
bx G"
bx F"
bx E"
bx D"
bx A"
b0 @"
b0 ?"
bx <"
bx 9"
bx 8"
bx 7"
bx 6"
bx 3"
b0 2"
b0 1"
bx /"
bx ,"
bx +"
bx *"
bx )"
bx &"
b0 %"
b0 $"
bx ""
bx }
bx |
bx {
bx z
bx w
b0 v
b0 u
bx s
bx p
bx o
bx n
bx m
bx j
b0 i
b0 h
bx e
bx b
bx a
bx `
bx _
bx \
b0 [
b0 Z
bx X
bx U
bx T
bx S
bx R
bx O
b0 N
b0 M
bx K
bx H
bx G
bx F
bx E
bx B
b0 A
b0 @
bx >
bx ;
bx :
bx 9
bx 8
bx 5
b0 4
b0 3
b100 ,
b100 +
1*
0)
0(
0'
0&
0%
$end
#5000
b0 5
b0 >
b0 9
b0 ;
b0 8
b0 :
b0 B
b0 K
b0 F
b0 H
b0 E
b0 G
b0 O
b0 X
b0 S
b0 U
b0 R
b0 T
b0 \
b0 e
b0 `
b0 b
b0 _
b0 a
b0 j
b0 s
b0 n
b0 p
b0 m
b0 o
b0 w
b0 ""
b0 {
b0 }
b0 z
b0 |
b0 &"
b0 /"
b0 *"
b0 ,"
b0 )"
b0 +"
b0 3"
b0 <"
b0 7"
b0 9"
b0 6"
b0 8"
b0 A"
b0 J"
b0 E"
b0 G"
b0 D"
b0 F"
b0 N"
b0 W"
b0 R"
b0 T"
b0 Q"
b0 S"
b0 ["
b0 d"
b0 _"
b0 a"
b0 ^"
b0 `"
b0 h"
b0 q"
b0 l"
b0 n"
b0 k"
b0 m"
b0 v"
b0 !#
b0 z"
b0 |"
b0 y"
b0 {"
b0 %#
b0 .#
b0 )#
b0 +#
b0 (#
b0 *#
b0 2#
b0 ;#
b0 6#
b0 8#
b0 5#
b0 7#
b0 ?#
b0 H#
b0 C#
b0 E#
b0 B#
b0 D#
1&
#10000
0&
#15000
b10 >#
b110 =#
b10 1#
b101 0#
b10 $#
b100 ##
b10 u"
b11 t"
b10 g"
b101 f"
b10 Z"
b100 Y"
b10 M"
b11 L"
b10 @"
b10 ?"
b10 2"
b100 1"
b10 %"
b11 $"
b10 v
b10 u
b10 i
b1 h
b10 [
b11 Z
b10 N
b10 M
b10 A
b1 @
b10 4
b100 ,
b100 +
0*
1&
#20000
1)
1(
0&
#25000
b10 9
b10 ;
b10 F
b10 H
b1 E
b1 G
b10 S
b10 U
b10 R
b10 T
b10 `
b10 b
b11 _
b11 a
b10 n
b10 p
b1 m
b1 o
b10 {
b10 }
b10 z
b10 |
b10 *"
b10 ,"
b11 )"
b11 +"
b10 7"
b10 9"
b100 6"
b100 8"
b10 E"
b10 G"
b10 D"
b10 F"
b10 R"
b10 T"
b11 Q"
b11 S"
b10 _"
b10 a"
b100 ^"
b100 `"
b10 l"
b10 n"
b101 k"
b101 m"
b10 z"
b10 |"
b11 y"
b11 {"
b10 )#
b10 +#
b100 (#
b100 *#
b10 6#
b10 8#
b101 5#
b101 7#
b10 C#
b10 E#
b110 B#
b110 D#
1&
#30000
0)
0(
0&
#35000
1&
#40000
1'
0&
#45000
b10 B
b10 K
b100 O
b100 X
b110 \
b110 e
b10 j
b10 s
b100 w
b100 ""
b110 &"
b110 /"
b1000 3"
b1000 <"
b100 A"
b100 J"
b110 N"
b110 W"
b1000 ["
b1000 d"
b1010 h"
b1010 q"
b110 v"
b110 !#
b1000 %#
b1000 .#
b1010 2#
b1010 ;#
b1100 ?#
b1100 H#
1&
#50000
0'
0&
#55000
1&
#60000
0&
#65000
b11 >#
b1 =#
b11 1#
b1 0#
b11 $#
b1 ##
b11 u"
b1 t"
b11 g"
b1 f"
b11 Z"
b1 Y"
b11 M"
b1 L"
b11 @"
b1 ?"
b11 2"
b1 1"
b11 %"
b1 $"
b11 v
b1 u
b11 i
b11 [
b1 Z
b11 N
b1 M
b11 A
b11 4
b1 3
b100 ,
b100 +
1&
#70000
1)
1(
0&
#75000
b11 C#
b11 E#
b1 B#
b1 D#
b11 6#
b11 8#
b1 5#
b1 7#
b11 )#
b11 +#
b1 (#
b1 *#
b11 z"
b11 |"
b1 y"
b1 {"
b11 l"
b11 n"
b1 k"
b1 m"
b11 _"
b11 a"
b1 ^"
b1 `"
b11 R"
b11 T"
b1 Q"
b1 S"
b11 E"
b11 G"
b1 D"
b1 F"
b11 7"
b11 9"
b1 6"
b1 8"
b11 *"
b11 ,"
b1 )"
b1 +"
b11 {
b11 }
b1 z
b1 |
b11 n
b11 p
b11 `
b11 b
b1 _
b1 a
b11 S
b11 U
b1 R
b1 T
b11 F
b11 H
b11 9
b11 ;
b1 8
b1 :
1&
#80000
0)
0(
0&
#85000
1&
#90000
1'
0&
